CHANGELOG.md
LICENSE
MANIFEST.in
README.md
setup.cfg
setup.py
pip_services3_datadog/__init__.py
pip_services3_datadog.egg-info/PKG-INFO
pip_services3_datadog.egg-info/SOURCES.txt
pip_services3_datadog.egg-info/dependency_links.txt
pip_services3_datadog.egg-info/requires.txt
pip_services3_datadog.egg-info/top_level.txt
pip_services3_datadog.egg-info/zip-safe
pip_services3_datadog/build/DefaultDataDogFactory.py
pip_services3_datadog/build/__init__.py
pip_services3_datadog/clients/DataDogLogClient.py
pip_services3_datadog/clients/DataDogLogMessage.py
pip_services3_datadog/clients/DataDogMetric.py
pip_services3_datadog/clients/DataDogMetricPoint.py
pip_services3_datadog/clients/DataDogMetricType.py
pip_services3_datadog/clients/DataDogMetricsClient.py
pip_services3_datadog/clients/DataDogStatus.py
pip_services3_datadog/clients/__init__.py
pip_services3_datadog/count/DataDogCounters.py
pip_services3_datadog/count/__init__.py
pip_services3_datadog/log/DataDogLogger.py
pip_services3_datadog/log/__init__.py
test/clients/__init__.py
test/clients/test_DataDogLogClient.py
test/clients/test_DataDogMetricClient.py
test/count/__init__.py
test/count/test_DataDogCounters.py
test/fixtures/CountersFixture.py
test/fixtures/LoggerFixture.py
test/fixtures/__init__.py
test/log/__init__.py
test/log/test_DataDogLogger.py